pyautoport/__init__.py
pyautoport/adb.py
pyautoport/session.py
pyautoport/teraterm.py
pyautoport/uart.py
pyautoport/addon/__init__.py
pyautoport/addon/adb.py
pyautoport/addon/addon.py
pyautoport/addon/tty.py
pyautoport-1.3.1.dist-info/licenses/LICENSE
pyautoport-1.3.1.dist-info/METADATA
pyautoport-1.3.1.dist-info/WHEEL
pyautoport-1.3.1.dist-info/entry_points.txt
pyautoport-1.3.1.dist-info/top_level.txt
pyautoport-1.3.1.dist-info/RECORD
