Metadata-Version: 2.4
Name: pyAutoPort
Version: 1.3.1
Summary: A tool automating UART and ADB interaction
Author: Yu GU
Author-email: yu.gu@sony.com
License: BSD-3-Clause
Project-URL: Homepage, https://github.com/sony/pyAutoPort
Project-URL: Issues, https://github.com/sony/pyAutoPort/issues
Classifier: Programming Language :: Python :: 3
Requires-Python: >=3.8
License-File: LICENSE
Requires-Dist: pyserial
Dynamic: author
Dynamic: author-email
Dynamic: classifier
Dynamic: description
Dynamic: description-content-type
Dynamic: license
Dynamic: license-file
Dynamic: project-url
Dynamic: requires-dist
Dynamic: requires-python
Dynamic: summary
